LICENSE
django_editorjs_fields/__init__.py
django_editorjs_fields/config.py
django_editorjs_fields/fields.py
django_editorjs_fields/static/django-editorjs-fields/css/django-editorjs-fields.css
django_editorjs_fields/static/django-editorjs-fields/js/django-editorjs-fields.js
django_editorjs_fields/templates/django-editorjs-fields/widget.html
django_editorjs_fields/templatetags/__init__.py
django_editorjs_fields/templatetags/editorjs.py
django_editorjs_fields/urls.py
django_editorjs_fields/utils.py
django_editorjs_fields/views.py
django_editorjs_fields/widgets.py
django_editorjs_fields-0.2.6.dist-info/LICENSE
django_editorjs_fields-0.2.6.dist-info/WHEEL
django_editorjs_fields-0.2.6.dist-info/METADATA
django_editorjs_fields-0.2.6.dist-info/RECORD
