Metadata-Version: 2.1
Name: django-editorjs-fields
Version: 0.2.6
Summary: Django plugin for using Editor.js
Home-page: https://github.com/2ik/django-editorjs-fields
License: MIT
Keywords: editorjs,django-editor,django-wysiwyg,wysiwyg,django-admin
Author: Ilya Kotlyakov
Author-email: m@2ik.ru
Requires-Python: >=3.6,<4.0
Classifier: Development Status :: 5 - Production/Stable
Classifier: Framework :: Django
Classifier: Framework :: Django :: 2.2
Classifier: Framework :: Django :: 3.0
Classifier: Framework :: Django :: 3.1
Classifier: Framework :: Django :: 3.2
Classifier: Intended Audience :: Developers
Classifier: License :: OSI Approved :: MIT License
Classifier: Operating System :: OS Independent
Classifier: Programming Language :: Python :: 3
Classifier: Programming Language :: Python :: 3 :: Only
Classifier: Programming Language :: Python :: 3.10
Classifier: Programming Language :: Python :: 3.6
Classifier: Programming Language :: Python :: 3.7
Classifier: Programming Language :: Python :: 3.8
Classifier: Programming Language :: Python :: 3.9
Classifier: Topic :: Software Development :: Libraries :: Application Frameworks
Classifier: Topic :: Software Development :: Libraries :: Python Modules
Project-URL: Documentation, https://github.com/2ik/django-editorjs-fields
Project-URL: Repository, https://github.com/2ik/django-editorjs-fields
